drawitor/__init__.py
drawitor/__main__.py
drawitor/cli.py
drawitor/core.py
drawitor/utils.py
drawitor-0.1.1.dist-info/entry_points.txt
drawitor-0.1.1.dist-info/WHEEL
drawitor-0.1.1.dist-info/METADATA
drawitor-0.1.1.dist-info/RECORD
