Metadata-Version: 2.1
Name: drawitor
Version: 0.1.1
Summary: Draw Images or GIFs in your terminal.
Home-page: https://github.com/UltiRequiem/drawitor
Keywords: commands,utilities,cli
Author: Eliaz Bobadilla
Author-email: eliaz.bobadilladev@gmail.com
Requires-Python: >=3.10,<4.0
Classifier: Programming Language :: Python :: 3
Classifier: Programming Language :: Python :: 3.10
Requires-Dist: Pillow (>=9.0.1,<10.0.0)
Project-URL: Repository, https://github.com/UltiRequiem/drawitor
